{
  "$schema": "https://developer.microsoft.com/json-schemas/fabric/item/report/definition/visualContainer/2.4.0/schema.json",
  "name": "d8ed8940ebd65a07ab30",
  "position": {
    "x": 31.616090331686664,
    "y": 97.558221594918848,
    "z": 11000,
    "height": 108.39802399435428,
    "width": 284.54481298518,
    "tabOrder": 11000
  },
  "visual": {
    "visualType": "slicer",
    "query": {
      "queryState": {
        "Values": {
          "projections": [
            {
              "field": {
                "Column": {
                  "Expression": {
                    "SourceRef": {
                      "Entity": "TAX"
                    }
                  },
                  "Property": "TAX"
                }
              },
              "queryRef": "TAX.TAX",
              "nativeQueryRef": "TAX",
              "active": true
            }
          ]
        }
      }
    },
    "objects": {
      "data": [
        {
          "properties": {
            "numericStart": {
              "expr": {
                "Literal": {
                  "Value": "1.2000000000000002D"
                }
              }
            }
          }
        }
      ],
      "general": [
        {
          "properties": {
            "filter": {
              "filter": {
                "Version": 2,
                "From": [
                  {
                    "Name": "t",
                    "Entity": "TAX",
                    "Type": 0
                  }
                ],
                "Where": [
                  {
                    "Condition": {
                      "Comparison": {
                        "ComparisonKind": 0,
                        "Left": {
                          "Column": {
                            "Expression": {
                              "SourceRef": {
                                "Source": "t"
                              }
                            },
                            "Property": "TAX"
                          }
                        },
                        "Right": {
                          "Literal": {
                            "Value": "1.2000000000000002D"
                          }
                        }
                      }
                    }
                  }
                ]
              }
            }
          }
        }
      ]
    },
    "drillFilterOtherVisuals": true
  }
}